content_hash/__init__.py
content_hash/__main__.py
content_hash/py.typed
content_hash/utils.py
content_hash/decodes/__init__.py
content_hash/decodes/b58_multi_hash.py
content_hash/decodes/hex_multi_hash.py
content_hash/decodes/utf8.py
content_hash/encodes/__init__.py
content_hash/encodes/ipfs.py
content_hash/encodes/swarm.py
content_hash/encodes/utf8.py
content_hash/profiles/__init__.py
content_hash-2.0.0.dist-info/LICENSE
content_hash-2.0.0.dist-info/METADATA
content_hash-2.0.0.dist-info/WHEEL
content_hash-2.0.0.dist-info/top_level.txt
content_hash-2.0.0.dist-info/RECORD
