Metadata-Version: 2.1
Name: content-hash
Version: 2.0.0
Summary: Python implementation of EIP 1577 content hash
Author-email: Filip Š <projects@filips.si>
License: MIT License
Project-URL: Homepage, https://github.com/filips123/ContentHashPy/
Project-URL: Repository, https://github.com/filips123/ContentHashPy.git
Project-URL: Issues, https://github.com/filips123/ContentHashPy/issues
Project-URL: Changelog, https://github.com/filips123/ContentHashPy/releases
Keywords: ethereum,ethereum-name-service,ens,eip1577,erc1577,web3,decentralized
Classifier: Development Status :: 5 - Production/Stable
Classifier: Intended Audience :: Developers
Classifier: License :: OSI Approved :: MIT License
Classifier: Programming Language :: Python :: 3
Classifier: Topic :: Internet :: Name Service (DNS)
Classifier: Topic :: Scientific/Engineering :: Interface Engine/Protocol Translator
Classifier: Topic :: Security :: Cryptography
Classifier: Topic :: Software Development :: Libraries
Classifier: Topic :: Utilities
Classifier: Typing :: Typed
Requires-Python: >=3.8
License-File: LICENSE
Requires-Dist: multiformats >=0.3.1.post4
Requires-Dist: base58check ==1.0.2
Requires-Dist: pycryptodomex
Provides-Extra: lint
Requires-Dist: pylint ; extra == 'lint'
Requires-Dist: black ; extra == 'lint'
Requires-Dist: mypy ; extra == 'lint'
Provides-Extra: test
Requires-Dist: pytest ; extra == 'test'
Requires-Dist: pytest-cov ; extra == 'test'
